ogt/__init__.py
ogt/ags4.py
ogt/ogt_cell.py
ogt/ogt_doc.py
ogt/ogt_group.py
ogt/ogt_heading.py
ogt/ogt_validate.py
ogt/utils.py
ogt/thirdparty/__init__.py
ogt/thirdparty/bng_to_latlon.py
ogt/thirdparty/latlon_to_bng.py
ogtgui/Qt.py
ogtgui/__init__.py
ogtgui/ags4_models.py
ogtgui/ags4_widgets.py
ogtgui/app_globals.py
ogtgui/img.py
ogtgui/main_window.py
ogtgui/map_widgets.py
ogtgui/ogtgui_dialogs.py
ogtgui/ogtgui_doc.py
ogtgui/ogtgui_errors.py
ogtgui/ogtgui_excel.py
ogtgui/ogtgui_group.py
ogtgui/ogtgui_groups.py
ogtgui/ogtgui_project.py
ogtgui/ogtgui_projects.py
ogtgui/ogtgui_samples.py
ogtgui/ogtgui_schedules.py
ogtgui/ogtgui_sources.py
ogtgui/ogtgui_widgets.py
ogtgui/settings.py
ogtgui/www_client.py
ogtgui/xobjects.py
ogtgui/xwidgets.py
ogtserver/__init__.py
ogtserver/main.py
ogtstatic/__init__.py
ogtstatic/ags4.min.json
ogtstatic/ags4_examples.min.json
ogtstatic/version.txt
open_geotechnical-0.1.8.data/data/share/applications/open-geotechnical.desktop
open_geotechnical-0.1.8.data/data/share/icons/32x32/apps/open-geotechnical.png
open_geotechnical-0.1.8.data/scripts/ogt-cli.py
open_geotechnical-0.1.8.data/scripts/ogt-desktop.py
open_geotechnical-0.1.8.data/scripts/ogt-server.sh
open_geotechnical-0.1.8.dist-info/LICENSE
open_geotechnical-0.1.8.dist-info/METADATA
open_geotechnical-0.1.8.dist-info/WHEEL
open_geotechnical-0.1.8.dist-info/top_level.txt
open_geotechnical-0.1.8.dist-info/RECORD
